betatim_fragala-0.1.dist-info/DESCRIPTION.rst
betatim_fragala-0.1.dist-info/METADATA
betatim_fragala-0.1.dist-info/RECORD
betatim_fragala-0.1.dist-info/WHEEL
betatim_fragala-0.1.dist-info/dependency_links.txt
betatim_fragala-0.1.dist-info/metadata.json
betatim_fragala-0.1.dist-info/top_level.txt
fragala/__init__.py
